[{"id":537,"league_name":"ASIA : World Championship - Qualification - Second stage - Round 4","home_name":"Lebanon","home_logo":"https:\/\/static.flashscore.com\/res\/image\/data\/ALVjjRh5-QNrz0V5B.png","away_name":"Australia","away_logo":"https:\/\/static.flashscore.com\/res\/image\/data\/Ygu7zgHG-YNb3oHYR.png","event_date":"2024-03-26","event_time":"15:15:00","original_event_url":"https:\/\/www.flashfootball.com\/match\/SnExjSWK\/","live_event_url":"https:\/\/vebotv.mba\/truc-tiep\/lebanon-vs-australia-26-03-2024-1545\/","status":1,"created_at":"2024-03-26T04:38:05.000000Z","updated_at":"2024-03-26T04:38:05.000000Z"},{"id":539,"league_name":"ASIA : World Championship - Qualification - Second stage - Round 4","home_name":"Bangladesh","home_logo":"https:\/\/static.flashscore.com\/res\/image\/data\/ClcfoVh5-Au8oKy8P.png","away_name":"Palestine","away_logo":"https:\/\/static.flashscore.com\/res\/image\/data\/pUqCDBYA-zmDbXBOa.png","event_date":"2024-03-26","event_time":"16:00:00","original_event_url":"https:\/\/www.flashfootball.com\/match\/Qcx5rYFq\/","live_event_url":"https:\/\/vebotv.mba\/truc-tiep\/bangladesh-vs-palestine-26-03-2024-1630\/","status":1,"created_at":"2024-03-26T04:39:56.000000Z","updated_at":"2024-03-26T04:39:56.000000Z"},{"id":538,"league_name":"ASIA : World Championship - Qualification - Second stage - Round 4","home_name":"Vietnam","home_logo":"https:\/\/static.flashscore.com\/res\/image\/data\/rZCKbaFa-QHeKqeWC.png","away_name":"Indonesia","away_logo":"https:\/\/static.flashscore.com\/res\/image\/data\/WvrcHkXg-QBz8eAFI.png","event_date":"2024-03-26","event_time":"18:30:00","original_event_url":"https:\/\/www.flashfootball.com\/match\/42QKkAO2\/","live_event_url":"https:\/\/vebotv.mba\/truc-tiep\/vietnam-vs-indonesia-26-03-2024-1900\/","status":1,"created_at":"2024-03-26T04:39:10.000000Z","updated_at":"2024-03-26T04:39:10.000000Z"}]